Workbook

Sheet Инвестиции
A1: Наименование статьи затрат | B1: Всего за проект | C1: 1 мес | D1: 2 мес | E1: 3 мес | F1: 4 мес | G1: 5 мес | H1: 6 мес | I1: 7 мес | J1: 8 мес | K1: 9 мес | L1: 10 мес | M1: 11 мес | N1: 12 мес | O1: 13 мес | P1: 14 мес | Q1: 15 мес | R1: 16 мес | S1: 17 мес | T1: 18 мес | U1: 19 мес | V1: 20 мес | W1: 21 мес | X1: 22 мес | Y1: 23 мес | Z1: 24 мес | AA1: 25 мес | AB1: 26 мес | AC1: 27 мес | AD1: 28 мес | AE1: 29 мес | AF1: 30 мес | AG1: 31 мес | AH1: 32 мес | AI1: 33 мес | AJ1: 34 мес | AK1: 35 мес | AL1: 36 мес
A2: 1. Приобретение оборудования и материалов | B2: 470000 | C2: 470000 | D2: 0 | E2: 0 | F2: 0 | G2: 0 | H2: 0 | I2: 0 | J2: 0 | K2: 0 | L2: 0 | M2: 0 | N2: 0 | O2: 0 | P2: 0 | Q2: 0 | R2: 0 | S2: 0 | T2: 0 | U2: 0 | V2: 0 | W2: 0 | X2: 0 | Y2: 0 | Z2: 0 | AA2: 0 | AB2: 0 | AC2: 0 | AD2: 0 | AE2: 0 | AF2: 0 | AG2: 0 | AH2: 0 | AI2: 0 | AJ2: 0 | AK2: 0 | AL2: 0
A3: 2. Услуги контрагентов | B3: 110000 | C3: 110000 | D3: 0 | E3: 0 | F3: 0 | G3: 0 | H3: 0 | I3: 0 | J3: 0 | K3: 0 | L3: 0 | M3: 0 | N3: 0 | O3: 0 | P3: 0 | Q3: 0 | R3: 0 | S3: 0 | T3: 0 | U3: 0 | V3: 0 | W3: 0 | X3: 0 | Y3: 0 | Z3: 0 | AA3: 0 | AB3: 0 | AC3: 0 | AD3: 0 | AE3: 0 | AF3: 0 | AG3: 0 | AH3: 0 | AI3: 0 | AJ3: 0 | AK3: 0 | AL3: 0
A4: 3. Регистрация, сайт, интеллектуальная собственность | B4: 120000 | C4: 120000 | D4: 0 | E4: 0 | F4: 0 | G4: 0 | H4: 0 | I4: 0 | J4: 0 | K4: 0 | L4: 0 | M4: 0 | N4: 0 | O4: 0 | P4: 0 | Q4: 0 | R4: 0 | S4: 0 | T4: 0 | U4: 0 | V4: 0 | W4: 0 | X4: 0 | Y4: 0 | Z4: 0 | AA4: 0 | AB4: 0 | AC4: 0 | AD4: 0 | AE4: 0 | AF4: 0 | AG4: 0 | AH4: 0 | AI4: 0 | AJ4: 0 | AK4: 0 | AL4: 0
A5: ИТОГО ИНВЕСТИЦИОННЫЕ РАСХОДЫ | B5: 700000 | C5: 700000 | D5: 0 | E5: 0 | F5: 0 | G5: 0 | H5: 0 | I5: 0 | J5: 0 | K5: 0 | L5: 0 | M5: 0 | N5: 0 | O5: 0 | P5: 0 | Q5: 0 | R5: 0 | S5: 0 | T5: 0 | U5: 0 | V5: 0 | W5: 0 | X5: 0 | Y5: 0 | Z5: 0 | AA5: 0 | AB5: 0 | AC5: 0 | AD5: 0 | AE5: 0 | AF5: 0 | AG5: 0 | AH5: 0 | AI5: 0 | AJ5: 0 | AK5: 0 | AL5: 0

Sheet Доходы
A1: Наименование показателя | B1: Формула | C1: 1 мес | D1: 2 мес | E1: 3 мес | F1: 4 мес | G1: 5 мес | H1: 6 мес | I1: 7 мес | J1: 8 мес | K1: 9 мес | L1: 10 мес | M1: 11 мес | N1: 12 мес | O1: 13 мес | P1: 14 мес | Q1: 15 мес | R1: 16 мес | S1: 17 мес | T1: 18 мес | U1: 19 мес | V1: 20 мес | W1: 21 мес | X1: 22 мес | Y1: 23 мес | Z1: 24 мес | AA1: 25 мес | AB1: 26 мес | AC1: 27 мес | AD1: 28 мес | AE1: 29 мес | AF1: 30 мес | AG1: 31 мес | AH1: 32 мес | AI1: 33 мес | AJ1: 34 мес | AK1: 35 мес | AL1: 36 мес
A2: 1. ВЕРТИКАЛЬНАЯ КОЛОННА
A3: Кол-во продаж (шт) | B3: План | C3: 0 | D3: 0 | E3: 0 | F3: 0 | G3: 0 | H3: 0 | I3: 0 | J3: 0 | K3: 0 | L3: 0 | M3: 0 | N3: 0 | O3: 10 | P3: 15 | Q3: 30 | R3: 30 | S3: 30 | T3: 30 | U3: 30 | V3: 30 | W3: 30 | X3: 30 | Y3: 35 | Z3: 35 | AA3: 50 | AB3: 40 | AC3: 40 | AD3: 40 | AE3: 40 | AF3: 40 | AG3: 40 | AH3: 40 | AI3: 40 | AJ3: 40 | AK3: 50 | AL3: 50
A4: Цена за 1 шт | B4: Ввод | C4: 20000 | D4: 20000 | E4: 20000 | F4: 20000 | G4: 20000 | H4: 20000 | I4: 20000 | J4: 20000 | K4: 20000 | L4: 20000 | M4: 20000 | N4: 20000 | O4: 20000 | P4: 20000 | Q4: 20000 | R4: 20000 | S4: 20000 | T4: 20000 | U4: 20000 | V4: 20000 | W4: 20000 | X4: 20000 | Y4: 20000 | Z4: 20000 | AA4: 20000 | AB4: 20000 | AC4: 20000 | AD4: 20000 | AE4: 20000 | AF4: 20000 | AG4: 20000 | AH4: 20000 | AI4: 20000 | AJ4: 20000 | AK4: 20000 | AL4: 20000
A5: Выручка (Колонна) | B5: Кол-во*Цена | C5: =C3*C4 -> 0 | D5: =D3*D4 -> 0 | E5: =E3*E4 -> 0 | F5: =F3*F4 -> 0 | G5: =G3*G4 -> 0 | H5: =H3*H4 -> 0 | I5: =I3*I4 -> 0 | J5: =J3*J4 -> 0 | ... AL5: =AL3*AL4 -> 1000000
A6: 2. ЯРУСНАЯ СИСТЕМА
A7: Кол-во продаж (шт) | B7: План | C7: 0 | D7: 0 | E7: 0 | F7: 0 | G7: 0 | H7: 0 | I7: 0 | J7: 0 | K7: 0 | L7: 0 | M7: 0 | N7: 0 | O7: 3 | P7: 5 | Q7: 10 | R7: 10 | S7: 10 | T7: 10 | U7: 10 | V7: 10 | W7: 10 | X7: 10 | Y7: 15 | Z7: 15 | AA7: 18 | AB7: 18 | AC7: 18 | AD7: 18 | AE7: 18 | AF7: 18 | AG7: 18 | AH7: 18 | AI7: 18 | AJ7: 18 | AK7: 20 | AL7: 20
A8: Цена за 1 шт | B8: Ввод | C8: 60000 | D8: 60000 | E8: 60000 | F8: 60000 | G8: 60000 | H8: 60000 | I8: 60000 | J8: 60000 | K8: 60000 | L8: 60000 | M8: 60000 | N8: 60000 | O8: 60000 | P8: 60000 | Q8: 60000 | R8: 60000 | S8: 60000 | T8: 60000 | U8: 60000 | V8: 60000 | W8: 60000 | X8: 60000 | Y8: 60000 | Z8: 60000 | AA8: 60000 | AB8: 60000 | AC8: 60000 | AD8: 60000 | AE8: 60000 | AF8: 60000 | AG8: 60000 | AH8: 60000 | AI8: 60000 | AJ8: 60000 | AK8: 60000 | AL8: 60000
A9: Выручка (Ярус) | B9: Кол-во*Цена | C9: =C8*C7 -> 0 | D9: =D8*D7 -> 0 | E9: =E8*E7 -> 0 | F9: =F8*F7 -> 0 | G9: =G8*G7 -> 0 | H9: =H8*H7 -> 0 | I9: =I8*I7 -> 0 | J9: =J8*J7 -> 0 | ... AL9: =AL8*AL7 -> 1200000
A10: ИТОГО ВЫРУЧКА | B10: Сумма выручки | C10: =SUM(C5,C9) -> 0 | D10: =SUM(D5,D9) -> 0 | E10: =SUM(E5,E9) -> 0 | F10: =SUM(F5,F9) -> 0 | G10: =SUM(G5,G9) -> 0 | H10: =SUM(H5,H9) -> 0 | I10: =SUM(I5,I9) -> 0 | J10: =SUM(J5,J9) -> 0 | ... AL10: =SUM(AL5,AL9) -> 2200000

Sheet Расходы
A1: Наименование показателя | B1: Формула | C1: 1 мес | D1: 2 мес | E1: 3 мес | F1: 4 мес | G1: 5 мес | H1: 6 мес | I1: 7 мес | J1: 8 мес | K1: 9 мес | L1: 10 мес | M1: 11 мес | N1: 12 мес | O1: 13 мес | P1: 14 мес | Q1: 15 мес | R1: 16 мес | S1: 17 мес | T1: 18 мес | U1: 19 мес | V1: 20 мес | W1: 21 мес | X1: 22 мес | Y1: 23 мес | Z1: 24 мес | AA1: 25 мес | AB1: 26 мес | AC1: 27 мес | AD1: 28 мес | AE1: 29 мес | AF1: 30 мес | AG1: 31 мес | AH1: 32 мес | AI1: 33 мес | AJ1: 34 мес | AK1: 35 мес | AL1: 36 мес
A2: 1. СЕБЕСТОИМОСТЬ: ВЕРТИКАЛЬНАЯ КОЛОННА (20 000 руб)
A3: Пластиковый корпус (ABS-пластик) | B3: Ввод | C3: 3000 | D3: 3000 | E3: 3000 | F3: 3000 | G3: 3000 | H3: 3000 | I3: 3000 | J3: 3000 | K3: 3000 | L3: 3000 | M3: 3000 | N3: 3000 | O3: 3000 | P3: 3000 | Q3: 3000 | R3: 3000 | S3: 3000 | T3: 3000 | U3: 3000 | V3: 3000 | W3: 3000 | X3: 3000 | Y3: 3000 | Z3: 3000 | AA3: 3000 | AB3: 3000 | AC3: 3000 | AD3: 3000 | AE3: 3000 | AF3: 3000 | AG3: 3000 | AH3: 3000 | AI3: 3000 | AJ3: 3000 | AK3: 3000 | AL3: 3000
A4: Система полива (насос, трубки) | B4: Ввод | C4: 2000 | D4: 2000 | E4: 2000 | F4: 2000 | G4: 2000 | H4: 2000 | I4: 2000 | J4: 2000 | K4: 2000 | L4: 2000 | M4: 2000 | N4: 2000 | O4: 2000 | P4: 2000 | Q4: 2000 | R4: 2000 | S4: 2000 | T4: 2000 | U4: 2000 | V4: 2000 | W4: 2000 | X4: 2000 | Y4: 2000 | Z4: 2000 | AA4: 2000 | AB4: 2000 | AC4: 2000 | AD4: 2000 | AE4: 2000 | AF4: 2000 | AG4: 2000 | AH4: 2000 | AI4: 2000 | AJ4: 2000 | AK4: 2000 | AL4: 2000
A5: Светодиодные лампы | B5: Ввод | C5: 2500 | D5: 2500 | E5: 2500 | F5: 2500 | G5: 2500 | H5: 2500 | I5: 2500 | J5: 2500 | K5: 2500 | L5: 2500 | M5: 2500 | N5: 2500 | O5: 2500 | P5: 2500 | Q5: 2500 | R5: 2500 | S5: 2500 | T5: 2500 | U5: 2500 | V5: 2500 | W5: 2500 | X5: 2500 | Y5: 2500 | Z5: 2500 | AA5: 2500 | AB5: 2500 | AC5: 2500 | AD5: 2500 | AE5: 2500 | AF5: 2500 | AG5: 2500 | AH5: 2500 | AI5: 2500 | AJ5: 2500 | AK5: 2500 | AL5: 2500
A6: Расходники и упаковка | B6: Ввод | C6: 500 | D6: 500 | E6: 500 | F6: 500 | G6: 500 | H6: 500 | I6: 500 | J6: 500 | K6: 500 | L6: 500 | M6: 500 | N6: 500 | O6: 500 | P6: 500 | Q6: 500 | R6: 500 | S6: 500 | T6: 500 | U6: 500 | V6: 500 | W6: 500 | X6: 500 | Y6: 500 | Z6: 500 | AA6: 500 | AB6: 500 | AC6: 500 | AD6: 500 | AE6: 500 | AF6: 500 | AG6: 500 | AH6: 500 | AI6: 500 | AJ6: 500 | AK6: 500 | AL6: 500
A7: Сборка (сдельная оплата за 1 шт) | B7: Ввод | C7: 2000 | D7: 2000 | E7: 2000 | F7: 2000 | G7: 2000 | H7: 2000 | I7: 2000 | J7: 2000 | K7: 2000 | L7: 2000 | M7: 2000 | N7: 2000 | O7: 2000 | P7: 2000 | Q7: 2000 | R7: 2000 | S7: 2000 | T7: 2000 | U7: 2000 | V7: 2000 | W7: 2000 | X7: 2000 | Y7: 2000 | Z7: 2000 | AA7: 2000 | AB7: 2000 | AC7: 2000 | AD7: 2000 | AE7: 2000 | AF7: 2000 | AG7: 2000 | AH7: 2000 | AI7: 2000 | AJ7: 2000 | AK7: 2000 | AL7: 2000
A8: ИТОГО СЕБЕСТОИМОСТЬ КОЛОННЫ | B8: СУММ | C8: =SUM(C3:C7) -> 10000 | D8: =SUM(D3:D7) -> 10000 | E8: =SUM(E3:E7) -> 10000 | F8: =SUM(F3:F7) -> 10000 | G8: =SUM(G3:G7) -> 10000 | H8: =SUM(H3:H7) -> 10000 | I8: =SUM(I3:I7) -> 10000 | J8: =SUM(J3:J7) -> 10000 | ... AL8: =SUM(AL3:AL7) -> 10000
A9: 2. СЕБЕСТОИМОСТЬ: ЯРУСНАЯ СИСТЕМА (60 000 руб)
A10: Алюминиевый каркас и поддоны | B10: Ввод | C10: 15000 | D10: 15000 | E10: 15000 | F10: 15000 | G10: 15000 | H10: 15000 | I10: 15000 | J10: 15000 | K10: 15000 | L10: 15000 | M10: 15000 | N10: 15000 | O10: 15000 | P10: 15000 | Q10: 15000 | R10: 15000 | S10: 15000 | T10: 15000 | U10: 15000 | V10: 15000 | W10: 15000 | X10: 15000 | Y10: 15000 | Z10: 15000 | AA10: 15000 | AB10: 15000 | AC10: 15000 | AD10: 15000 | AE10: 15000 | AF10: 15000 | AG10: 15000 | AH10: 15000 | AI10: 15000 | AJ10: 15000 | AK10: 15000 | AL10: 15000
A11: Проф. освещение и автоматика | B11: Ввод | C11: 10000 | D11: 10000 | E11: 10000 | F11: 10000 | G11: 10000 | H11: 10000 | I11: 10000 | J11: 10000 | K11: 10000 | L11: 10000 | M11: 10000 | N11: 10000 | O11: 10000 | P11: 10000 | Q11: 10000 | R11: 10000 | S11: 10000 | T11: 10000 | U11: 10000 | V11: 10000 | W11: 10000 | X11: 10000 | Y11: 10000 | Z11: 10000 | AA11: 10000 | AB11: 10000 | AC11: 10000 | AD11: 10000 | AE11: 10000 | AF11: 10000 | AG11: 10000 | AH11: 10000 | AI11: 10000 | AJ11: 10000 | AK11: 10000 | AL11: 10000
A12: Мощные насосы и фильтры | B12: Ввод | C12: 8000 | D12: 8000 | E12: 8000 | F12: 8000 | G12: 8000 | H12: 8000 | I12: 8000 | J12: 8000 | K12: 8000 | L12: 8000 | M12: 8000 | N12: 8000 | O12: 8000 | P12: 8000 | Q12: 8000 | R12: 8000 | S12: 8000 | T12: 8000 | U12: 8000 | V12: 8000 | W12: 8000 | X12: 8000 | Y12: 8000 | Z12: 8000 | AA12: 8000 | AB12: 8000 | AC12: 8000 | AD12: 8000 | AE12: 8000 | AF12: 8000 | AG12: 8000 | AH12: 8000 | AI12: 8000 | AJ12: 8000 | AK12: 8000 | AL12: 8000
A13: Расходники и упаковка | B13: Ввод | C13: 2000 | D13: 2000 | E13: 2000 | F13: 2000 | G13: 2000 | H13: 2000 | I13: 2000 | J13: 2000 | K13: 2000 | L13: 2000 | M13: 2000 | N13: 2000 | O13: 2000 | P13: 2000 | Q13: 2000 | R13: 2000 | S13: 2000 | T13: 2000 | U13: 2000 | V13: 2000 | W13: 2000 | X13: 2000 | Y13: 2000 | Z13: 2000 | AA13: 2000 | AB13: 2000 | AC13: 2000 | AD13: 2000 | AE13: 2000 | AF13: 2000 | AG13: 2000 | AH13: 2000 | AI13: 2000 | AJ13: 2000 | AK13: 2000 | AL13: 2000
A14: Сборка (сдельная оплата за 1 шт) | B14: Ввод | C14: 5000 | D14: 5000 | E14: 5000 | F14: 5000 | G14: 5000 | H14: 5000 | I14: 5000 | J14: 5000 | K14: 5000 | L14: 5000 | M14: 5000 | N14: 5000 | O14: 5000 | P14: 5000 | Q14: 5000 | R14: 5000 | S14: 5000 | T14: 5000 | U14: 5000 | V14: 5000 | W14: 5000 | X14: 5000 | Y14: 5000 | Z14: 5000 | AA14: 5000 | AB14: 5000 | AC14: 5000 | AD14: 5000 | AE14: 5000 | AF14: 5000 | AG14: 5000 | AH14: 5000 | AI14: 5000 | AJ14: 5000 | AK14: 5000 | AL14: 5000
A15: ИТОГО СЕБЕСТОИМОСТЬ ЯРУСА | B15: СУММ | C15: =SUM(C10:C14) -> 40000 | D15: =SUM(D10:D14) -> 40000 | E15: =SUM(E10:E14) -> 40000 | F15: =SUM(F10:F14) -> 40000 | G15: =SUM(G10:G14) -> 40000 | H15: =SUM(H10:H14) -> 40000 | I15: =SUM(I10:I14) -> 40000 | J15: =SUM(J10:J14) -> 40000 | ... AL15: =SUM(AL10:AL14) -> 40000
A16: 3. ПОСТОЯННЫЕ РАСХОДЫ (В МЕСЯЦ)
A17: Аренда цеха и склада | B17: Ввод | C17: 0 | D17: 0 | E17: 0 | F17: 0 | G17: 0 | H17: 0 | I17: 0 | J17: 0 | K17: 0 | L17: 0 | M17: 0 | N17: 0 | O17: 50000 | P17: 50000 | Q17: 50000 | R17: 50000 | S17: 50000 | T17: 50000 | U17: 50000 | V17: 50000 | W17: 50000 | X17: 50000 | Y17: 50000 | Z17: 50000 | AA17: 50000 | AB17: 50000 | AC17: 50000 | AD17: 50000 | AE17: 50000 | AF17: 50000 | AG17: 50000 | AH17: 50000 | AI17: 50000 | AJ17: 50000 | AK17: 50000 | AL17: 50000
A18: Маркетинг (Сайт, реклама) | B18: Ввод | C18: 0 | D18: 0 | E18: 0 | F18: 0 | G18: 0 | H18: 0 | I18: 0 | J18: 0 | K18: 0 | L18: 0 | M18: 0 | N18: 0 | O18: 40000 | P18: 40000 | Q18: 40000 | R18: 40000 | S18: 40000 | T18: 40000 | U18: 40000 | V18: 40000 | W18: 40000 | X18: 40000 | Y18: 40000 | Z18: 40000 | AA18: 40000 | AB18: 40000 | AC18: 40000 | AD18: 40000 | AE18: 40000 | AF18: 40000 | AG18: 40000 | AH18: 40000 | AI18: 40000 | AJ18: 40000 | AK18: 40000 | AL18: 40000
A19: Прочие (Связь, Банк, Интернет) | B19: Ввод | C19: 0 | D19: 0 | E19: 0 | F19: 0 | G19: 0 | H19: 0 | I19: 0 | J19: 0 | K19: 0 | L19: 0 | M19: 0 | N19: 0 | O19: 10000 | P19: 10000 | Q19: 10000 | R19: 10000 | S19: 10000 | T19: 10000 | U19: 10000 | V19: 10000 | W19: 10000 | X19: 10000 | Y19: 10000 | Z19: 10000 | AA19: 10000 | AB19: 10000 | AC19: 10000 | AD19: 10000 | AE19: 10000 | AF19: 10000 | AG19: 10000 | AH19: 10000 | AI19: 10000 | AJ19: 10000 | AK19: 10000 | AL19: 10000
A20: 4. ПЕРЕМЕННЫЕ РАСХОДЫ ОТ ПЛАНА
A21: ВЕРТИКАЛЬНАЯ КОЛОННА
A22: Кол-во продаж (шт) | B22: План | C22: =Доходы!C3 -> 0 | D22: =Доходы!D3 -> 0 | E22: =Доходы!E3 -> 0 | F22: =Доходы!F3 -> 0 | G22: =Доходы!G3 -> 0 | H22: =Доходы!H3 -> 0 | I22: =Доходы!I3 -> 0 | J22: =Доходы!J3 -> 0 | ... AL22: =Доходы!AL3 -> 50
A23: ПЕРЕМЕННЫЕ РАСХОДЫ | B23: Количество*себестоимость | C23: =C22*C8 -> 0 | D23: =D22*D8 -> 0 | E23: =E22*E8 -> 0 | F23: =F22*F8 -> 0 | G23: =G22*G8 -> 0 | H23: =H22*H8 -> 0 | I23: =I22*I8 -> 0 | J23: =J22*J8 -> 0 | ... AL23: =AL22*AL8 -> 500000
A24: ЯРУСНАЯ СИСТЕМА
A25: Кол-во продаж (шт) | B25: План | C25: =Доходы!C7 -> 0 | D25: =Доходы!D7 -> 0 | E25: =Доходы!E7 -> 0 | F25: =Доходы!F7 -> 0 | G25: =Доходы!G7 -> 0 | H25: =Доходы!H7 -> 0 | I25: =Доходы!I7 -> 0 | J25: =Доходы!J7 -> 0 | ... AL25: =Доходы!AL7 -> 20
A26: ПЕРЕМЕННЫЕ РАСХОДЫ | B26: Количество*себестоимость | C26: =C25*C15 -> 0 | D26: =D25*D15 -> 0 | E26: =E25*E15 -> 0 | F26: =F25*F15 -> 0 | G26: =G25*G15 -> 0 | H26: =H25*H15 -> 0 | I26: =I25*I15 -> 0 | J26: =J25*J15 -> 0 | ... AL26: =AL25*AL15 -> 800000
A27: ИТОГО ПЕРЕМЕННЫЕ РАСХОДЫ | B27: Расходы Ярусная+Вертикальная | C27: =C26+C23 -> 0 | D27: =D26+D23 -> 0 | E27: =E26+E23 -> 0 | F27: =F26+F23 -> 0 | G27: =G26+G23 -> 0 | H27: =H26+H23 -> 0 | I27: =I26+I23 -> 0 | J27: =J26+J23 -> 0 | ... AL27: =AL26+AL23 -> 1300000

Sheet ФОТ
A1: Наименование должности | B1: Формула | C1: 1 мес | D1: 2 мес | E1: 3 мес | F1: 4 мес | G1: 5 мес | H1: 6 мес | I1: 7 мес | J1: 8 мес | K1: 9 мес | L1: 10 мес | M1: 11 мес | N1: 12 мес | O1: 13 мес | P1: 14 мес | Q1: 15 мес | R1: 16 мес | S1: 17 мес | T1: 18 мес | U1: 19 мес | V1: 20 мес | W1: 21 мес | X1: 22 мес | Y1: 23 мес | Z1: 24 мес | AA1: 25 мес | AB1: 26 мес | AC1: 27 мес | AD1: 28 мес | AE1: 29 мес | AF1: 30 мес | AG1: 31 мес | AH1: 32 мес | AI1: 33 мес | AJ1: 34 мес | AK1: 35 мес | AL1: 36 мес
A2: Директор | B2: Ввод | C2: 15000 | D2: 15000 | E2: 15000 | F2: 15000 | G2: 15000 | H2: 15000 | I2: 15000 | J2: 15000 | K2: 15000 | L2: 15000 | M2: 15000 | N2: 15000 | O2: 15000 | P2: 15000 | Q2: 15000 | R2: 15000 | S2: 15000 | T2: 15000 | U2: 15000 | V2: 15000 | W2: 15000 | X2: 15000 | Y2: 15000 | Z2: 15000 | AA2: 15000 | AB2: 15000 | AC2: 15000 | AD2: 15000 | AE2: 15000 | AF2: 15000 | AG2: 15000 | AH2: 15000 | AI2: 15000 | AJ2: 15000 | AK2: 15000 | AL2: 15000
A3: Разработчик системы | B3: Ввод | C3: 19230 | D3: 19230 | E3: 19230 | F3: 19230 | G3: 19230 | H3: 19230 | I3: 19230 | J3: 19230 | K3: 19230 | L3: 19230 | M3: 19230 | N3: 19230 | O3: 70000 | P3: 70000 | Q3: 70000 | R3: 70000 | S3: 70000 | T3: 70000 | U3: 70000 | V3: 70000 | W3: 70000 | X3: 70000 | Y3: 70000 | Z3: 70000 | AA3: 70000 | AB3: 70000 | AC3: 70000 | AD3: 70000 | AE3: 70000 | AF3: 70000 | AG3: 70000 | AH3: 70000 | AI3: 70000 | AJ3: 70000 | AK3: 70000 | AL3: 70000
A4: Бухгалтер | B4: Ввод | C4: 15000 | D4: 15000 | E4: 15000 | F4: 15000 | G4: 15000 | H4: 15000 | I4: 15000 | J4: 15000 | K4: 15000 | L4: 15000 | M4: 15000 | N4: 15000 | O4: 15000 | P4: 15000 | Q4: 15000 | R4: 15000 | S4: 15000 | T4: 15000 | U4: 15000 | V4: 15000 | W4: 15000 | X4: 15000 | Y4: 15000 | Z4: 15000 | AA4: 15000 | AB4: 15000 | AC4: 15000 | AD4: 15000 | AE4: 15000 | AF4: 15000 | AG4: 15000 | AH4: 15000 | AI4: 15000 | AJ4: 15000 | AK4: 15000 | AL4: 15000
A5: ИТОГО ФОТ (Начисленная ЗП) | B5: Сумма | C5: =SUM(C2:C4) -> 49230 | D5: =SUM(D2:D4) -> 49230 | E5: =SUM(E2:E4) -> 49230 | F5: =SUM(F2:F4) -> 49230 | G5: =SUM(G2:G4) -> 49230 | H5: =SUM(H2:H4) -> 49230 | I5: =SUM(I2:I4) -> 49230 | J5: =SUM(J2:J4) -> 49230 | ... AL5: =SUM(AL2:AL4) -> 100000
A6: Страховые взносы на персонал (30%) | B6: ФОТ * 30% | C6: =C5*30% -> 14769 | D6: =D5*30% -> 14769 | E6: =E5*30% -> 14769 | F6: =F5*30% -> 14769 | G6: =G5*30% -> 14769 | H6: =H5*30% -> 14769 | I6: =I5*30% -> 14769 | J6: =J5*30% -> 14769 | ... AL6: =AL5*30% -> 30000

Sheet БДР
A1: Наименование показателя | B1: Формула в Excel | C1: 1 мес | D1: 2 мес | E1: 3 мес | F1: 4 мес | G1: 5 мес | H1: 6 мес | I1: 7 мес | J1: 8 мес | K1: 9 мес | L1: 10 мес | M1: 11 мес | N1: 12 мес | O1: 13 мес | P1: 14 мес | Q1: 15 мес | R1: 16 мес | S1: 17 мес | T1: 18 мес | U1: 19 мес | V1: 20 мес | W1: 21 мес | X1: 22 мес | Y1: 23 мес | Z1: 24 мес | AA1: 25 мес | AB1: 26 мес | AC1: 27 мес | AD1: 28 мес | AE1: 29 мес | AF1: 30 мес | AG1: 31 мес | AH1: 32 мес | AI1: 33 мес | AJ1: 34 мес | AK1: 35 мес | AL1: 36 мес
A2: ВЫРУЧКА (Колонны + Ярусные) | B2: Доходы!Итого | C2: =Доходы!C10 -> 0 | D2: =Доходы!D10 -> 0 | E2: =Доходы!E10 -> 0 | F2: =Доходы!F10 -> 0 | G2: =Доходы!G10 -> 0 | H2: =Доходы!H10 -> 0 | I2: =Доходы!I10 -> 0 | J2: =Доходы!J10 -> 0 | ... AL2: =Доходы!AL10 -> 2200000
A3: СЕБЕСТОИМОСТЬ ОБЩАЯ (Колонны + Ярусные) | B3: Расходы!Общие Переменные | C3: =Расходы!C27 -> 0 | D3: =Расходы!D27 -> 0 | E3: =Расходы!E27 -> 0 | F3: =Расходы!F27 -> 0 | G3: =Расходы!G27 -> 0 | H3: =Расходы!H27 -> 0 | I3: =Расходы!I27 -> 0 | J3: =Расходы!J27 -> 0 | ... AL3: =Расходы!AL27 -> 1300000
A4: ВАЛОВАЯ ПРИБЫЛЬ | B4: Выручка - Себестоимость | C4: =C2-C3 -> 0 | D4: =D2-D3 -> 0 | E4: =E2-E3 -> 0 | F4: =F2-F3 -> 0 | G4: =G2-G3 -> 0 | H4: =H2-H3 -> 0 | I4: =I2-I3 -> 0 | J4: =J2-J3 -> 0 | ... AL4: =AL2-AL3 -> 900000
A5: ПОСТОЯННЫЕ РАСХОДЫ
A6: ФОТ (Зарплаты) | B6: ФОТ!Итого | C6: =ФОТ!C5 -> 49230 | D6: =ФОТ!D5 -> 49230 | E6: =ФОТ!E5 -> 49230 | F6: =ФОТ!F5 -> 49230 | G6: =ФОТ!G5 -> 49230 | H6: =ФОТ!H5 -> 49230 | I6: =ФОТ!I5 -> 49230 | J6: =ФОТ!J5 -> 49230 | ... AL6: =ФОТ!AL5 -> 100000
A7: Страховые взносы | B7: ФОТ!Взносы | C7: =ФОТ!C6 -> 14769 | D7: =ФОТ!D6 -> 14769 | E7: =ФОТ!E6 -> 14769 | F7: =ФОТ!F6 -> 14769 | G7: =ФОТ!G6 -> 14769 | H7: =ФОТ!H6 -> 14769 | I7: =ФОТ!I6 -> 14769 | J7: =ФОТ!J6 -> 14769 | ... AL7: =ФОТ!AL6 -> 30000
A8: Аренда помещения | B8: Расходы!Аренда | C8: =Расходы!C17 -> 0 | D8: =Расходы!D17 -> 0 | E8: =Расходы!E17 -> 0 | F8: =Расходы!F17 -> 0 | G8: =Расходы!G17 -> 0 | H8: =Расходы!H17 -> 0 | I8: =Расходы!I17 -> 0 | J8: =Расходы!J17 -> 0 | ... AL8: =Расходы!AL17 -> 50000
A9: Маркетинг и реклама | B9: Расходы!Маркетинг | C9: =Расходы!C18 -> 0 | D9: =Расходы!D18 -> 0 | E9: =Расходы!E18 -> 0 | F9: =Расходы!F18 -> 0 | G9: =Расходы!G18 -> 0 | H9: =Расходы!H18 -> 0 | I9: =Расходы!I18 -> 0 | J9: =Расходы!J18 -> 0 | ... AL9: =Расходы!AL18 -> 40000
A10: Прочие расходы | B10: Расходы!Прочие | C10: =Расходы!C19 -> 0 | D10: =Расходы!D19 -> 0 | E10: =Расходы!E19 -> 0 | F10: =Расходы!F19 -> 0 | G10: =Расходы!G19 -> 0 | H10: =Расходы!H19 -> 0 | I10: =Расходы!I19 -> 0 | J10: =Расходы!J19 -> 0 | ... AL10: =Расходы!AL19 -> 10000
A11: ИТОГО ПОСТОЯННЫЕ РАСХОДЫ | B11: СУММ(4.1 : 4.5) | C11: =SUM(C6:C10) -> 63999 | D11: =SUM(D6:D10) -> 63999 | E11: =SUM(E6:E10) -> 63999 | F11: =SUM(F6:F10) -> 63999 | G11: =SUM(G6:G10) -> 63999 | H11: =SUM(H6:H10) -> 63999 | I11: =SUM(I6:I10) -> 63999 | J11: =SUM(J6:J10) -> 63999 | ... AL11: =SUM(AL6:AL10) -> 230000
A12: ОПЕРАЦИОННАЯ ПРИБЫЛЬ (EBITDA) | B12: Валовая - Постоянные | C12: =C4-C11 -> -63999 | D12: =D4-D11 -> -63999 | E12: =E4-E11 -> -63999 | F12: =F4-F11 -> -63999 | G12: =G4-G11 -> -63999 | H12: =H4-H11 -> -63999 | I12: =I4-I11 -> -63999 | J12: =J4-J11 -> -63999 | ... AL12: =AL4-AL11 -> 670000
A13: НАЛОГИ (УСН 15%) | B13: ЕСЛИ(EBITDA>0; EBITDA*0,15; 0) | C13: =IF(C12>0,C12*0.15,0) -> 0 | D13: =IF(D12>0,D12*0.15,0) -> 0 | E13: =IF(E12>0,E12*0.15,0) -> 0 | F13: =IF(F12>0,F12*0.15,0) -> 0 | G13: =IF(G12>0,G12*0.15,0) -> 0 | H13: =IF(H12>0,H12*0.15,0) -> 0 | I13: =IF(I12>0,I12*0.15,0) -> 0 | J13: =IF(J12>0,J12*0.15,0) -> 0 | ... AL13: =IF(AL12>0,AL12*0.15,0) -> 100500
A14: ЧИСТАЯ ПРИБЫЛЬ | B14: EBITDA - Налоги | C14: =C12-C13 -> -63999 | D14: =D12-D13 -> -63999 | E14: =E12-E13 -> -63999 | F14: =F12-F13 -> -63999 | G14: =G12-G13 -> -63999 | H14: =H12-H13 -> -63999 | I14: =I12-I13 -> -63999 | J14: =J12-J13 -> -63999 | ... AL14: =AL12-AL13 -> 569500
A16: Наименование показателя | B16: Год 1 (Разработка) | C16: Год 2 (Итого) | D16: Год 3 (Итого)
A17: ОПЕРАЦИОННЫЕ ПОКАЗАТЕЛИ
A18: 1. ВЫРУЧКА | B18: =SUM($C2:$N2) -> 0 | C18: =SUM($O2:$Z2) -> 13780000 | D18: =SUM($AA2:$AL2) -> 23400000
A19: 2. ПЕРЕМЕННЫЕ РАСХОДЫ | B19: =SUM($C3:$N3) -> 0 | C19: =SUM($O3:$Z3) -> 8070000 | D19: =SUM($AA7:$AL7) -> 360000
A20: 3. ВАЛОВАЯ ПРИБЫЛЬ | B20: =SUM($C4:$N4) -> 0 | C20: =SUM($O4:$Z4) -> 5710000 | D20: =SUM($AA4:$AL4) -> 9500000
A21: Рентабельность по валовой прибыли | B21: 0 | C21: =C20/C18 -> 0.41436865 | D21: =D20/D18 -> 0.40598291
A22: 4. ПОСТОЯННЫЕ РАСХОДЫ
A23: 4.1. ФОТ (Зарплаты) | B23: =SUM(C7:N7) -> 177228 | C23: =SUM(O7:Z7) -> 360000 | D23: =SUM(AA7:AL7) -> 360000
A24: 4.2. Страховые взносы | B24: =B23*30% -> 53168.4 | C24: =C23*30% -> 108000 | D24: =D23*30% -> 108000
A25: 4.3. Аренда помещения | B25: =SUM(C8:N8) -> 0 | C25: =SUM(O13:Z13) -> 453000 | D25: =SUM(AA8:AL8) -> 600000
A26: 4.4. Маркетинг и реклама | B26: =SUM(C9:N9) -> 0 | C26: =SUM(O9:Z9) -> 480000 | D26: =SUM(AA9:AL9) -> 480000
A27: 4.5. Прочие расходы (интернет, ПО) | B27: =SUM(C10:N10) -> 0 | C27: =SUM(O10:Z10) -> 120000 | D27: =SUM(AA10:AL10) -> 120000
A28: ИТОГО ПОСТОЯННЫЕ РАСХОДЫ | B28: =SUM(C11:N11) -> 767988 | C28: =SUM(O11:Z11) -> 2760000 | D28: =SUM(AA11:AL11) -> 2760000
A29: 5. ОПЕРАЦИОННАЯ ПРИБЫЛЬ (EBITDA) | B29: =B20-B28 -> -767988 | C29: =C20-C28 -> 2950000 | D29: =D20-D28 -> 6740000
A30: 6. НАЛОГИ
A31: Единый налог (УСН 15%) | B31: =IF(B29>0, B29*15%, 0) -> 0 | C31: =IF(C29>0, C29*15%, 0) -> 442500 | D31: =IF(D29>0, D29*15%, 0) -> 1011000
A32: 7. ЧИСТАЯ ПРИБЫЛЬ | B32: =B29-B31 -> -767988 | C32: =C29-C31 -> 2507500 | D32: =D29-D31 -> 5729000

Sheet ОДДС
A1: Наименование показателя | B1: Формула | C1: 1 мес | D1: 2 мес | E1: 3 мес | F1: 4 мес | G1: 5 мес | H1: 6 мес | I1: 7 мес | J1: 8 мес | K1: 9 мес | L1: 10 мес | M1: 11 мес | N1: 12 мес | O1: 13 мес | P1: 14 мес | Q1: 15 мес | R1: 16 мес | S1: 17 мес | T1: 18 мес | U1: 19 мес | V1: 20 мес | W1: 21 мес | X1: 22 мес | Y1: 23 мес | Z1: 24 мес | AA1: 25 мес | AB1: 26 мес | AC1: 27 мес | AD1: 28 мес | AE1: 29 мес | AF1: 30 мес | AG1: 31 мес | AH1: 32 мес | AI1: 33 мес | AJ1: 34 мес | AK1: 35 мес | AL1: 36 мес
A2: Остаток денег НА НАЧАЛО месяца | B2: Предыдущий Остаток на КОНЕЦ | C2: 0 | D2: =C16 -> 236001 | E2: =D16 -> 172002 | F2: =E16 -> 108003 | G2: =F16 -> 44004 | H2: =G16 -> -19995 | I2: =H16 -> -83994 | J2: =I16 -> -147993 | K2: =J16 -> -211992 | ... AL2: =AK16 -> 7188512
A3: 1. ПОСТУПЛЕНИЯ ДЕНЕГ (ПРИТОК)
A4: 1.1. Грант (ФСИ) | B4: Ввод руками | C4: 1000000 | D4: 0 | E4: 0 | F4: 0 | G4: 0 | H4: 0 | I4: 0 | J4: 0 | K4: 0 | L4: 0 | M4: 0 | N4: 0 | O4: 0 | P4: 0 | Q4: 0 | R4: 0 | S4: 0 | T4: 0 | U4: 0 | V4: 0 | W4: 0 | X4: 0 | Y4: 0 | Z4: 0 | AA4: 0 | AB4: 0 | AC4: 0 | AD4: 0 | AE4: 0 | AF4: 0 | AG4: 0 | AH4: 0 | AI4: 0 | AJ4: 0 | AK4: 0 | AL4: 0
A5: 1.2. Поступления от продаж | B5: БДР!Выручка | C5: =БДР!C2 -> 0 | D5: =БДР!D2 -> 0 | E5: =БДР!E2 -> 0 | F5: =БДР!F2 -> 0 | G5: =БДР!G2 -> 0 | H5: =БДР!H2 -> 0 | I5: =БДР!I2 -> 0 | J5: =БДР!J2 -> 0 | ... AM5: =БДР!AM2 -> 0
A6: ИТОГО ПОСТУПЛЕНИЙ | B6: СУММ(1.1:1.2) | C6: =SUM(C4:C5) -> 1000000 | D6: =SUM(D4:D5) -> 0 | E6: =SUM(E4:E5) -> 0 | F6: =SUM(F4:F5) -> 0 | G6: =SUM(G4:G5) -> 0 | H6: =SUM(H4:H5) -> 0 | I6: =SUM(I4:I5) -> 0 | J6: =SUM(J4:J5) -> 0 | ... AL6: =SUM(AL4:AL5) -> 2200000
A7: 2. ВЫБЫТИЯ ДЕНЕГ (ОТТОК)
A8: 2.1. Инвестиции (Оборудование, рег.) | B8: Инвестиции!Итого | C8: =Инвестиции!C5 -> 700000 | D8: 0 | E8: 0 | F8: 0 | G8: 0 | H8: 0 | I8: 0 | J8: 0 | K8: 0 | L8: 0 | M8: 0 | N8: 0 | O8: 0 | P8: 0 | Q8: 0 | R8: 0 | S8: 0 | T8: 0 | U8: 0 | V8: 0 | W8: 0 | X8: 0 | Y8: 0 | Z8: 0 | AA8: 0 | AB8: 0 | AC8: 0 | AD8: 0 | AE8: 0 | AF8: 0 | AG8: 0 | AH8: 0 | AI8: 0 | AJ8: 0 | AK8: 0 | AL8: 0
A9: 2.2. Закупка материалов (Переменные) | B9: БДР!Переменные расходы | C9: =БДР!C3 -> 0 | D9: =БДР!D3 -> 0 | E9: =БДР!E3 -> 0 | F9: =БДР!F3 -> 0 | G9: =БДР!G3 -> 0 | H9: =БДР!H3 -> 0 | I9: =БДР!I3 -> 0 | J9: =БДР!J3 -> 0 | ... AL9: =БДР!AL3 -> 1300000
A10: 2.3. Выплата зарплат (ФОТ) | B10: БДР!ФОТ | C10: =БДР!C6 -> 49230 | D10: =БДР!D6 -> 49230 | E10: =БДР!E6 -> 49230 | F10: =БДР!F6 -> 49230 | G10: =БДР!G6 -> 49230 | H10: =БДР!H6 -> 49230 | I10: =БДР!I6 -> 49230 | J10: =БДР!J6 -> 49230 | ... AL10: =БДР!AL6 -> 100000
A11: 2.4. Уплата страховых взносов | B11: БДР!Страховые взносы | C11: =БДР!C7 -> 14769 | D11: =БДР!D7 -> 14769 | E11: =БДР!E7 -> 14769 | F11: =БДР!F7 -> 14769 | G11: =БДР!G7 -> 14769 | H11: =БДР!H7 -> 14769 | I11: =БДР!I7 -> 14769 | J11: =БДР!J7 -> 14769 | ... AL11: =БДР!AL7 -> 30000
A12: 2.5. Оплата аренды, маркетинга, ПО | B12: БДР!Аренда+Маркетинг+Прочее | C12: =БДР!C8+БДР!C9+БДР!C10 -> 0 | D12: =БДР!D8+БДР!D9+БДР!D10 -> 0 | E12: =БДР!E8+БДР!E9+БДР!E10 -> 0 | F12: =БДР!F8+БДР!F9+БДР!F10 -> 0 | G12: =БДР!G8+БДР!G9+БДР!G10 -> 0 | H12: =БДР!H8+БДР!H9+БДР!H10 -> 0 | I12: =БДР!I8+БДР!I9+БДР!I10 -> 0 | J12: =БДР!J8+БДР!J9+БДР!J10 -> 0 | ... AL12: =БДР!AL8+БДР!AL9+БДР!AL10 -> 100000
A13: 2.6. Оплата налогов (УСН) | B13: БДР!Налоги | C13: =БДР!C13 -> 0 | D13: =БДР!D13 -> 0 | E13: =БДР!E13 -> 0 | F13: =БДР!F13 -> 0 | G13: =БДР!G13 -> 0 | H13: =БДР!H13 -> 0 | I13: =БДР!I13 -> 0 | J13: =БДР!J13 -> 0 | ... AL13: =БДР!AL13 -> 100500
A14: ИТОГО ВЫБЫТИЙ | B14: СУММ(2.1:2.6) | C14: =SUM(C8:C13) -> 763999 | D14: =SUM(D8:D13) -> 63999 | E14: =SUM(E8:E13) -> 63999 | F14: =SUM(F8:F13) -> 63999 | G14: =SUM(G8:G13) -> 63999 | H14: =SUM(H8:H13) -> 63999 | I14: =SUM(I8:I13) -> 63999 | J14: =SUM(J8:J13) -> 63999 | ... AL14: =SUM(AL8:AL13) -> 1630500
A15: 3. ЧИСТЫЙ ДЕНЕЖНЫЙ ПОТОК (NCF) | B15: ИТОГО ПОСТУПЛЕНИЙ - ИТОГО ВЫБЫТИЙ | C15: =C6-C14 -> 236001 | D15: =D6-D14 -> -63999 | E15: =E6-E14 -> -63999 | F15: =F6-F14 -> -63999 | G15: =G6-G14 -> -63999 | H15: =H6-H14 -> -63999 | I15: =I6-I14 -> -63999 | J15: =J6-J14 -> -63999 | ... AL15: =AL6-AL14 -> 569500
A16: Остаток денег НА КОНЕЦ месяца | B16: Остаток НА НАЧАЛО + NCF | C16: =C2+C15 -> 236001 | D16: =D2+D15 -> 172002 | E16: =E2+E15 -> 108003 | F16: =F2+F15 -> 44004 | G16: =G2+G15 -> -19995 | H16: =H2+H15 -> -83994 | I16: =I2+I15 -> -147993 | J16: =J2+J15 -> -211992 | ... AL16: =AL2+AL15 -> 7758012

Sheet Безубыточность
A1: 1. ВЕРТИКАЛЬНАЯ КОЛОННА
A2: Наименование показателя | B2: Формула | C2: 1 мес | D2: 2 мес | E2: 3 мес | F2: 4 мес | G2: 5 мес | H2: 6 мес | I2: 7 мес | J2: 8 мес | K2: 9 мес | L2: 10 мес | M2: 11 мес | N2: 12 мес | O2: 13 мес | P2: 14 мес | Q2: 15 мес | R2: 16 мес | S2: 17 мес | T2: 18 мес | U2: 19 мес | V2: 20 мес | W2: 21 мес | X2: 22 мес | Y2: 23 мес | Z2: 24 мес | AA2: 25 мес | AB2: 26 мес | AC2: 27 мес | AD2: 28 мес | AE2: 29 мес | AF2: 30 мес | AG2: 31 мес | AH2: 32 мес | AI2: 33 мес | AJ2: 34 мес | AK2: 35 мес | AL2: 36 мес
A3: 1. Цена за 1 установку | B3: Доходы!Цена | C3: =Доходы!C4 -> 20000 | D3: =Доходы!D4 -> 20000 | E3: =Доходы!E4 -> 20000 | F3: =Доходы!F4 -> 20000 | G3: =Доходы!G4 -> 20000 | H3: =Доходы!H4 -> 20000 | I3: =Доходы!I4 -> 20000 | J3: =Доходы!J4 -> 20000 | ... AL3: =Доходы!AL4 -> 20000
A4: 2. Переменные расходы (Себестоимость 1 шт) | B4: расходы!Себестоимость | C4: =Расходы!C8 -> 10000 | D4: =Расходы!D8 -> 10000 | E4: =Расходы!E8 -> 10000 | F4: =Расходы!F8 -> 10000 | G4: =Расходы!G8 -> 10000 | H4: =Расходы!H8 -> 10000 | I4: =Расходы!I8 -> 10000 | J4: =Расходы!J8 -> 10000 | ... AL4: =Расходы!AL8 -> 10000
A5: 3. МАРЖИНАЛЬНАЯ ПРИБЫЛЬ (с 1 шт) | B5: Цена - Себестоимость | C5: =C3-C4 -> 10000 | D5: =D3-D4 -> 10000 | E5: =E3-E4 -> 10000 | F5: =F3-F4 -> 10000 | G5: =G3-G4 -> 10000 | H5: =H3-H4 -> 10000 | I5: =I3-I4 -> 10000 | J5: =J3-J4 -> 10000 | ... AL5: =AL3-AL4 -> 10000
A6: 4. Итого Постоянные расходы за месяц | B6: БДР!Итого Постоянные | C6: =БДР!C11 -> 63999 | D6: =БДР!D11 -> 63999 | E6: =БДР!E11 -> 63999 | F6: =БДР!F11 -> 63999 | G6: =БДР!G11 -> 63999 | H6: =БДР!H11 -> 63999 | I6: =БДР!I11 -> 63999 | J6: =БДР!J11 -> 63999 | ... AL6: =БДР!AL11 -> 230000
A7: ТОЧКА БЕЗУБЫТОЧНОСТИ (в штуках) | B7: Постоянные / Маржинальную прибыль | C7: =C6/C5 -> 6.3999 | D7: =D6/D5 -> 6.3999 | E7: =E6/E5 -> 6.3999 | F7: =F6/F5 -> 6.3999 | G7: =G6/G5 -> 6.3999 | H7: =H6/H5 -> 6.3999 | I7: =I6/I5 -> 6.3999 | J7: =J6/J5 -> 6.3999 | ... AL7: =AL6/AL5 -> 23
A8: ТОЧКА БЕЗУБЫТОЧНОСТИ (в рублях) | B8: ТБ(шт) * Цена | C8: =C7*C3 -> 127998 | D8: =D7*D3 -> 127998 | E8: =E7*E3 -> 127998 | F8: =F7*F3 -> 127998 | G8: =G7*G3 -> 127998 | H8: =H7*H3 -> 127998 | I8: =I7*I3 -> 127998 | J8: =J7*J3 -> 127998 | ... AL8: =AL7*AL3 -> 460000
A9: Фактический план продаж (шт) | B9: БДР!Количество | C9: =Доходы!C3 -> 0 | D9: =Доходы!D3 -> 0 | E9: =Доходы!E3 -> 0 | F9: =Доходы!F3 -> 0 | G9: =Доходы!G3 -> 0 | H9: =Доходы!H3 -> 0 | I9: =Доходы!I3 -> 0 | J9: =Доходы!J3 -> 0 | ... AL9: =Доходы!AL3 -> 50
A10: Запас финансовой прочности (шт) | B10: Фактический план - ТБ(шт) | C10: =C9-C7 -> -6.3999 | D10: =D9-D7 -> -6.3999 | E10: =E9-E7 -> -6.3999 | F10: =F9-F7 -> -6.3999 | G10: =G9-G7 -> -6.3999 | H10: =H9-H7 -> -6.3999 | I10: =I9-I7 -> -6.3999 | J10: =J9-J7 -> -6.3999 | ... AL10: =AL9-AL7 -> 27
A11: 2. ЯРУСНАЯ СИСТЕМА
A12: Наименование показателя | B12: Формула | C12: 1 мес | D12: 2 мес | E12: 3 мес | F12: 4 мес | G12: 5 мес | H12: 6 мес | I12: 7 мес | J12: 8 мес | K12: 9 мес | L12: 10 мес | M12: 11 мес | N12: 12 мес | O12: 13 мес | P12: 14 мес | Q12: 15 мес | R12: 16 мес | S12: 17 мес | T12: 18 мес | U12: 19 мес | V12: 20 мес | W12: 21 мес | X12: 22 мес | Y12: 23 мес | Z12: 24 мес | AA12: 25 мес | AB12: 26 мес | AC12: 27 мес | AD12: 28 мес | AE12: 29 мес | AF12: 30 мес | AG12: 31 мес | AH12: 32 мес | AI12: 33 мес | AJ12: 34 мес | AK12: 35 мес | AL12: 36 мес
A13: 1. Цена за 1 установку | B13: доходыЦена | C13: =Доходы!C8 -> 60000 | D13: =Доходы!D8 -> 60000 | E13: =Доходы!E8 -> 60000 | F13: =Доходы!F8 -> 60000 | G13: =Доходы!G8 -> 60000 | H13: =Доходы!H8 -> 60000 | I13: =Доходы!I8 -> 60000 | J13: =Доходы!J8 -> 60000 | ... AL13: =Доходы!AL8 -> 60000
A14: 2. Переменные расходы (Себестоимость 1 шт) | B14: расходы!Себестоимость | C14: =Расходы!C15 -> 40000 | D14: =Расходы!D15 -> 40000 | E14: =Расходы!E15 -> 40000 | F14: =Расходы!F15 -> 40000 | G14: =Расходы!G15 -> 40000 | H14: =Расходы!H15 -> 40000 | I14: =Расходы!I15 -> 40000 | J14: =Расходы!J15 -> 40000 | ... AL14: =Расходы!AL15 -> 40000
A15: 3. МАРЖИНАЛЬНАЯ ПРИБЫЛЬ (с 1 шт) | B15: Цена - Себестоимость | C15: =C13-C14 -> 20000 | D15: =D13-D14 -> 20000 | E15: =E13-E14 -> 20000 | F15: =F13-F14 -> 20000 | G15: =G13-G14 -> 20000 | H15: =H13-H14 -> 20000 | I15: =I13-I14 -> 20000 | J15: =J13-J14 -> 20000 | ... AL15: =AL13-AL14 -> 20000
A16: 4. Итого Постоянные расходы за месяц | B16: расходы!Итого Постоянные | C16: =БДР!C11 -> 63999 | D16: =БДР!D11 -> 63999 | E16: =БДР!E11 -> 63999 | F16: =БДР!F11 -> 63999 | G16: =БДР!G11 -> 63999 | H16: =БДР!H11 -> 63999 | I16: =БДР!I11 -> 63999 | J16: =БДР!J11 -> 63999 | ... AL16: =БДР!AL11 -> 230000
A17: ТОЧКА БЕЗУБЫТОЧНОСТИ (в штуках) | B17: Постоянные / Маржинальную прибыль | C17: =C16/C15 -> 3.19995 | D17: =D16/D15 -> 3.19995 | E17: =E16/E15 -> 3.19995 | F17: =F16/F15 -> 3.19995 | G17: =G16/G15 -> 3.19995 | H17: =H16/H15 -> 3.19995 | I17: =I16/I15 -> 3.19995 | J17: =J16/J15 -> 3.19995 | ... AL17: =AL16/AL15 -> 11.5
A18: ТОЧКА БЕЗУБЫТОЧНОСТИ (в рублях) | B18: ТБ(шт) * Цена | C18: =C17*C13 -> 191997 | D18: =D17*D13 -> 191997 | E18: =E17*E13 -> 191997 | F18: =F17*F13 -> 191997 | G18: =G17*G13 -> 191997 | H18: =H17*H13 -> 191997 | I18: =I17*I13 -> 191997 | J18: =J17*J13 -> 191997 | ... AL18: =AL17*AL13 -> 690000
A19: Фактический план продаж (шт) | B19: БДР!Количество | C19: =Доходы!C7 -> 0 | D19: =Доходы!D7 -> 0 | E19: =Доходы!E7 -> 0 | F19: =Доходы!F7 -> 0 | G19: =Доходы!G7 -> 0 | H19: =Доходы!H7 -> 0 | I19: =Доходы!I7 -> 0 | J19: =Доходы!J7 -> 0 | ... AL19: =Доходы!AL7 -> 20
A20: Запас финансовой прочности (шт) | B20: Фактический план - ТБ(шт) | C20: =C19-C17 -> -3.19995 | D20: =D19-D17 -> -3.19995 | E20: =E19-E17 -> -3.19995 | F20: =F19-F17 -> -3.19995 | G20: =G19-G17 -> -3.19995 | H20: =H19-H17 -> -3.19995 | I20: =I19-I17 -> -3.19995 | J20: =J19-J17 -> -3.19995 | ... AL20: =AL19-AL17 -> 8.5
A21: 3. Общая (парные продажи)
A22: Наименование показателя | B22: Формула | C22: 1 мес | D22: 2 мес | E22: 3 мес | F22: 4 мес | G22: 5 мес | H22: 6 мес | I22: 7 мес | J22: 8 мес | K22: 9 мес | L22: 10 мес | M22: 11 мес | N22: 12 мес | O22: 13 мес | P22: 14 мес | Q22: 15 мес | R22: 16 мес | S22: 17 мес | T22: 18 мес | U22: 19 мес | V22: 20 мес | W22: 21 мес | X22: 22 мес | Y22: 23 мес | Z22: 24 мес | AA22: 25 мес | AB22: 26 мес | AC22: 27 мес | AD22: 28 мес | AE22: 29 мес | AF22: 30 мес | AG22: 31 мес | AH22: 32 мес | AI22: 33 мес | AJ22: 34 мес | AK22: 35 мес | AL22: 36 мес
A23: 1. Цена за 1 установку | B23: доходыЦена | C23: =Доходы!C4+Доходы!C8 -> 80000 | D23: =Доходы!D4+Доходы!D8 -> 80000 | E23: =Доходы!E4+Доходы!E8 -> 80000 | F23: =Доходы!F4+Доходы!F8 -> 80000 | G23: =Доходы!G4+Доходы!G8 -> 80000 | H23: =Доходы!H4+Доходы!H8 -> 80000 | I23: =Доходы!I4+Доходы!I8 -> 80000 | J23: =Доходы!J4+Доходы!J8 -> 80000 | ... AL23: =Доходы!AL4+Доходы!AL8 -> 80000
A24: 2. Переменные расходы (Себестоимость 1 шт) | B24: расходы!Себестоимость | C24: =Расходы!C15+Расходы!C8 -> 50000 | D24: =Расходы!D15+Расходы!D8 -> 50000 | E24: =Расходы!E15+Расходы!E8 -> 50000 | F24: =Расходы!F15+Расходы!F8 -> 50000 | G24: =Расходы!G15+Расходы!G8 -> 50000 | H24: =Расходы!H15+Расходы!H8 -> 50000 | I24: =Расходы!I15+Расходы!I8 -> 50000 | J24: =Расходы!J15+Расходы!J8 -> 50000 | ... AL24: =Расходы!AL15+Расходы!AL8 -> 50000
A25: 3. МАРЖИНАЛЬНАЯ ПРИБЫЛЬ (с 1 шт) | B25: Цена - Себестоимость | C25: =C23-C24 -> 30000 | D25: =D23-D24 -> 30000 | E25: =E23-E24 -> 30000 | F25: =F23-F24 -> 30000 | G25: =G23-G24 -> 30000 | H25: =H23-H24 -> 30000 | I25: =I23-I24 -> 30000 | J25: =J23-J24 -> 30000 | ... AL25: =AL23-AL24 -> 30000
A26: 4. Итого Постоянные расходы за месяц | B26: расходы!Итого Постоянные | C26: =БДР!C11 -> 63999 | D26: =БДР!D11 -> 63999 | E26: =БДР!E11 -> 63999 | F26: =БДР!F11 -> 63999 | G26: =БДР!G11 -> 63999 | H26: =БДР!H11 -> 63999 | I26: =БДР!I11 -> 63999 | J26: =БДР!J11 -> 63999 | ... AL26: =БДР!AL11 -> 230000
A27: ТОЧКА БЕЗУБЫТОЧНОСТИ (в штуках) | B27: Постоянные / Маржинальную прибыль | C27: =C26/C25 -> 2.1333 | D27: =D26/D25 -> 2.1333 | E27: =E26/E25 -> 2.1333 | F27: =F26/F25 -> 2.1333 | G27: =G26/G25 -> 2.1333 | H27: =H26/H25 -> 2.1333 | I27: =I26/I25 -> 2.1333 | J27: =J26/J25 -> 2.1333 | ... AL27: =AL26/AL25 -> 7.6666667
A28: ТОЧКА БЕЗУБЫТОЧНОСТИ (в рублях) | B28: ТБ(шт) * Цена | C28: =C27*C23 -> 170664 | D28: =D27*D23 -> 170664 | E28: =E27*E23 -> 170664 | F28: =F27*F23 -> 170664 | G28: =G27*G23 -> 170664 | H28: =H27*H23 -> 170664 | I28: =I27*I23 -> 170664 | J28: =J27*J23 -> 170664 | ... AL28: =AL27*AL23 -> 613333.33
A29: Фактический план продаж (шт) | B29: БДР!Количество | C29: =Доходы!C3+Доходы!C7 -> 0 | D29: =Доходы!D3+Доходы!D7 -> 0 | E29: =Доходы!E3+Доходы!E7 -> 0 | F29: =Доходы!F3+Доходы!F7 -> 0 | G29: =Доходы!G3+Доходы!G7 -> 0 | H29: =Доходы!H3+Доходы!H7 -> 0 | I29: =Доходы!I3+Доходы!I7 -> 0 | J29: =Доходы!J3+Доходы!J7 -> 0 | ... AL29: =Доходы!AL3+Доходы!AL7 -> 70
A30: Запас финансовой прочности (шт) | B30: Фактический план - ТБ(шт) | C30: =C29-C27 -> -2.1333 | D30: =D29-D27 -> -2.1333 | E30: =E29-E27 -> -2.1333 | F30: =F29-F27 -> -2.1333 | G30: =G29-G27 -> -2.1333 | H30: =H29-H27 -> -2.1333 | I30: =I29-I27 -> -2.1333 | J30: =J29-J27 -> -2.1333 | ... AL30: =AL29-AL27 -> 62.333333

Sheet Показатели эффективности
A1: Наименование показателя | B1: Формула в Excel | C1: 1 | D1: 2 | E1: 3 | F1: 4 | G1: 5 | H1: 6 | I1: 7 | J1: 8 | K1: 9 | L1: 10 | M1: 11 | N1: 12 | O1: 13 | P1: 14 | Q1: 15 | R1: 16 | S1: 17 | T1: 18 | U1: 19 | V1: 20 | W1: 21 | X1: 22 | Y1: 23 | Z1: 24 | AA1: 25 | AB1: 26 | AC1: 27 | AD1: 28 | AE1: 29 | AF1: 30 | AG1: 31 | AH1: 32 | AI1: 33 | AJ1: 34 | AK1: 35 | AL1: 36
A2: 1. Денежный поток проекта (FCFF) | B2: БДР!Чистая_Прибыль - Инвестиции!Итого | C2: =БДР!C14-Инвестиции!C5 -> -763999 | D2: =БДР!D14-Инвестиции!D5 -> -63999 | E2: =БДР!E14-Инвестиции!E5 -> -63999 | F2: =БДР!F14-Инвестиции!F5 -> -63999 | G2: =БДР!G14-Инвестиции!G5 -> -63999 | H2: =БДР!H14-Инвестиции!H5 -> -63999 | I2: =БДР!I14-Инвестиции!I5 -> -63999 | J2: =БДР!J14-Инвестиции!J5 -> -63999 | ... AL2: =БДР!AL14-Инвестиции!AL5 -> 569500
A3: 2. Ставка дисконтирования (Месячная) | B3: 25% / 12 месяцев | C3: 0.0208 | D3: 0.0208 | E3: 0.0208 | F3: 0.0208 | G3: 0.0208 | H3: 0.0208 | I3: 0.0208 | J3: 0.0208 | K3: 0.0208 | L3: 0.0208 | M3: 0.0208 | N3: 0.0208 | O3: 0.0208 | P3: 0.0208 | Q3: 0.0208 | R3: 0.0208 | S3: 0.0208 | T3: 0.0208 | U3: 0.0208 | V3: 0.0208 | W3: 0.0208 | X3: 0.0208 | Y3: 0.0208 | Z3: 0.0208 | AA3: 0.0208 | AB3: 0.0208 | AC3: 0.0208 | AD3: 0.0208 | AE3: 0.0208 | AF3: 0.0208 | AG3: 0.0208 | AH3: 0.0208 | AI3: 0.0208 | AJ3: 0.0208 | AK3: 0.0208 | AL3: 0.0208
A4: 3. Коэффициент дисконтирования | B4: 1 / ((1 + 2,08%)^Номер_месяца) | C4: =1/((1+2.08%)^C1) -> 0.97962382 | D4: =1/((1+2.08%)^D1) -> 0.95966284 | E4: =1/((1+2.08%)^E1) -> 0.94010858 | F4: =1/((1+2.08%)^F1) -> 0.92095276 | G4: =1/((1+2.08%)^G1) -> 0.90218727 | H4: =1/((1+2.08%)^H1) -> 0.88380414 | I4: =1/((1+2.08%)^I1) -> 0.86579559 | J4: =1/((1+2.08%)^J1) -> 0.84815399 | ... AL4: =1/((1+2.08%)^AL1) -> 0.47658041
A5: 4. ДИСКОНТИРОВАННЫЙ ПОТОК (DCF) | B5: Строка_1 * Строка_3 | C5: =C2*C4 -> -748431.62 | D5: =D2*D4 -> -61417.462 | E5: =E2*E4 -> -60166.009 | F5: =F2*F4 -> -58940.056 | G5: =G2*G4 -> -57739.083 | H5: =H2*H4 -> -56562.581 | I5: =I2*I4 -> -55410.052 | J5: =J2*J4 -> -54281.007 | ... AL5: =AL2*AL4 -> 271412.55
A6: 5. НАКОПЛЕННЫЙ DCF (Нарастающим) | B6: Предыдущий_накопленный + Текущий_DCF | C6: =C5 -> -748431.62 | D6: =D5+C6 -> -809849.08 | E6: =E5+D6 -> -870015.09 | F6: =F5+E6 -> -928955.15 | G6: =G5+F6 -> -986694.23 | H6: =H5+G6 -> -1043256.8 | I6: =I5+H6 -> -1098666.9 | J6: =J5+I6 -> -1152947.9 | K6: =K5+J6 -> -1206122.8 | ... AL6: =AL5+AK6 -> 3353973.4
A9: ИТОГОВЫЙ ПОКАЗАТЕЛЬ | B9: ЗНАЧЕНИЕ В EXCEL | C9: ФОРМУЛА (КАК СЧИТАТЬ)
A10: Ставка дисконтирования (WACC) | B10: 0.25 | C10: 15% (Ключевая ставка ЦБ РФ) + 10% (Премия за риск стартапа)
A11: NPV (Чистая приведенная стоимость) | B11: =AL6 -> 3353973.4 | C11: СУММ(всех ячеек строки 4 "DCF" за 36 месяцев)
A12: IRR (Внутренняя норма доходности) | B12: =IRR(C5:AL5) -> 0.057080063 | C12: ВНДОХ(Выделяешь все ячейки строки 1 "FCFF" за 36 месяцев)
A13: Срок окупаемости (PBP) | B13: 22 месяцев | C13: Месяц, когда в строке 5 "Накопленный DCF" минус сменился на плюс
A14: Индекс рентабельности (PI) | B14: =(B11+Инвестиции!C5)/Инвестиции!C5 -> 5.7913906 | C14: (NPV + Первоначальные Инвестиции) / Первоначальные Инвестиции

Sheet Резюме
A1: Показатель | B1: Год 1 (Разработка) | C1: Год 2 (Старт) | D1: Год 3 (Рост)
A2: Выручка, руб. | B2: =БДР!B18 -> 0 | C2: =БДР!C18 -> 13780000 | D2: =БДР!D18 -> 23400000
A3: Чистая прибыль, руб. | B3: =БДР!B32 -> -767988 | C3: =БДР!C32 -> 2507500 | D3: =БДР!D32 -> 5729000
A4: Рентабельность продаж, % | B4: 0 | C4: =C3/C2 -> 0.18196662 | D4: =D3/D2 -> 0.24482906
A5: Чистый денежный поток (NCF) | B5: =SUM(ОДДС!C15:N15) -> -467988 | C5: =SUM(ОДДС!O15:Z15) -> 2497000 | D5: =SUM(ОДДС!AA15:AL15) -> 5729000
A6: Количество проданных штук | B6: =SUM(Доходы!C3:N3) -> 0 | C6: =SUM(Доходы!O3:Z3,Доходы!O7:Z7) -> 453 | D6: =SUM(Доходы!AA3:AL3,Доходы!AA7:AL7) -> 730

Sheet Сценарии
A1: Сценарий | B1: Изменение факторов | C1: NPV (итоговый) | D1: Статус проекта
A2: Оптимистичный | B2: Продажи выше на 20% | C2: 4874351 | D2: Супер-прибыльно
A3: Реалистичный | B3: Всё идет по плану | C3: ='Показатели эффективности'!B11 -> 3353973.4 | D3: Устойчив
A4: Пессимистичный | B4: а продажи упали на 20% | C4: 1830222 | D4: Все равно выгодно
